Metadata-Version: 2.1
Name: argoptions
Version: 1.0.1
Summary: see tornado.options
Home-page: https://github.com/wzwjustdoit/argoptions
Author: wzwjustdoit
Author-email: wzwjustdoit@163.com
Maintainer: wzwjustdoit
Maintainer-email: wzwjustdoit@163.com
License: MIT
Keywords: argoptions,parser,opt,options,tornado,argv,sys
Platform: all
Classifier: License :: OSI Approved :: MIT License
Classifier: Programming Language :: Python
Classifier: Programming Language :: Python :: 3
Classifier: Programming Language :: Python :: 3.6
Classifier: Programming Language :: Python :: Implementation :: CPython
Classifier: Programming Language :: Python :: Implementation :: PyPy
Requires-Python: >=3.0.0
